{
  "line": "27",
  "name": "",
  "operator": "SADZV",
  "validFrom": "2026-04-20",
  "directions": [
    {
      "headsign": "Starohorská otočka",
      "stops": [
        {
          "name": "Podlavice,Gaštanová",
          "times": {
            "weekday": [
              "05:50",
              "06:23",
              "06:55",
              "07:23",
              "07:50",
              "08:30",
              "08:52",
              "13:37",
              "14:37",
              "15:13",
              "15:37",
              "16:13",
              "16:37",
              "17:09",
              "17:39"
            ],
            "weekend": [
              "22:50"
            ]
          }
        },
        {
          "name": "Povstalecká cesta",
          "times": {
            "weekday": [
              "05:51",
              "06:24",
              "06:56",
              "07:24",
              "07:51",
              "08:31",
              "08:53",
              "13:38",
              "14:38",
              "15:14",
              "15:38",
              "16:14",
              "16:38",
              "17:10",
              "17:40"
            ],
            "weekend": [
              "22:51"
            ]
          }
        },
        {
          "name": "Tajovského pod nemocnicou",
          "times": {
            "weekday": [
              "05:53",
              "06:26",
              "06:58",
              "07:26",
              "07:53",
              "08:33",
              "08:55",
              "13:40",
              "14:40",
              "15:16",
              "15:40",
              "16:16",
              "16:40",
              "17:12",
              "17:42"
            ],
            "weekend": [
              "22:52"
            ]
          }
        },
        {
          "name": "Tajovského,UMB",
          "times": {
            "weekday": [
              "05:54",
              "06:27",
              "06:59",
              "07:27",
              "07:54",
              "08:34",
              "08:56",
              "13:41",
              "14:41",
              "15:17",
              "15:41",
              "16:17",
              "16:41",
              "17:13",
              "17:43"
            ],
            "weekend": [
              "22:53"
            ]
          }
        },
        {
          "name": "Tajovského školy",
          "times": {
            "weekday": [
              "05:56",
              "06:29",
              "07:01",
              "07:29",
              "07:56",
              "08:36",
              "08:58",
              "13:43",
              "14:43",
              "15:19",
              "15:43",
              "16:19",
              "16:43",
              "17:15",
              "17:45"
            ],
            "weekend": [
              "22:54"
            ]
          }
        },
        {
          "name": "Tajovského,park",
          "times": {
            "weekday": [
              "05:58",
              "06:31",
              "07:03",
              "07:31",
              "07:58",
              "08:38",
              "09:00",
              "13:45",
              "14:45",
              "15:21",
              "15:45",
              "16:21",
              "16:45",
              "17:17",
              "17:47"
            ],
            "weekend": [
              "22:55"
            ]
          }
        },
        {
          "name": "Strieborné námestie",
          "times": {
            "weekday": [
              "05:59",
              "06:32",
              "07:04",
              "07:32",
              "07:59",
              "08:39",
              "09:01",
              "13:46",
              "14:46",
              "15:22",
              "15:46",
              "16:22",
              "16:46",
              "17:18",
              "17:48"
            ],
            "weekend": [
              "22:56"
            ]
          }
        },
        {
          "name": "Lazovná",
          "times": {
            "weekday": [
              "06:00",
              "06:33",
              "07:05",
              "07:33",
              "08:00",
              "08:40",
              "09:02",
              "13:47",
              "14:47",
              "15:23",
              "15:47",
              "16:23",
              "16:47",
              "17:19",
              "17:49"
            ],
            "weekend": [
              "22:57"
            ]
          }
        },
        {
          "name": "Severná",
          "times": {
            "weekday": [
              "06:01",
              "06:34",
              "07:06",
              "07:34",
              "08:01",
              "08:41",
              "09:03",
              "13:48",
              "14:48",
              "15:24",
              "15:48",
              "16:24",
              "16:48",
              "17:20",
              "17:50"
            ],
            "weekend": [
              "22:58"
            ]
          }
        },
        {
          "name": "Komenského",
          "times": {
            "weekday": [
              "06:02",
              "06:35",
              "07:07",
              "07:35",
              "08:02",
              "08:42",
              "09:04",
              "13:49",
              "14:49",
              "15:25",
              "15:49",
              "16:25",
              "16:49",
              "17:21",
              "17:51"
            ],
            "weekend": [
              "22:59"
            ]
          }
        },
        {
          "name": "Na Karlove",
          "times": {
            "weekday": [
              "06:03",
              "06:36",
              "07:08",
              "07:36",
              "08:03",
              "08:43",
              "09:05",
              "13:50",
              "14:50",
              "15:26",
              "15:50",
              "16:26",
              "16:50",
              "17:22",
              "17:52"
            ],
            "weekend": [
              "23:00"
            ]
          }
        },
        {
          "name": "Sásová,ihrisko",
          "times": {
            "weekday": [
              "06:05",
              "06:38",
              "07:10",
              "07:38",
              "08:05",
              "08:45",
              "09:07",
              "13:52",
              "14:52",
              "15:28",
              "15:52",
              "16:28",
              "16:52",
              "17:24",
              "17:54"
            ],
            "weekend": [
              "23:02"
            ]
          }
        },
        {
          "name": "Sásovská cesta",
          "times": {
            "weekday": [
              "06:06",
              "06:39",
              "07:11",
              "07:39",
              "08:06",
              "08:46",
              "09:08",
              "13:53",
              "14:53",
              "15:29",
              "15:53",
              "16:29",
              "16:53",
              "17:25",
              "17:55"
            ],
            "weekend": [
              "23:03"
            ]
          }
        },
        {
          "name": "Karpatská",
          "times": {
            "weekday": [
              "06:08",
              "06:41",
              "07:13",
              "07:41",
              "08:08",
              "08:48",
              "09:10",
              "13:55",
              "14:55",
              "15:31",
              "15:55",
              "16:31",
              "16:55",
              "17:27",
              "17:57"
            ],
            "weekend": [
              "23:05"
            ]
          }
        },
        {
          "name": "Rudohorská stred",
          "times": {
            "weekday": [
              "06:09",
              "06:42",
              "07:14",
              "07:42",
              "08:09",
              "08:49",
              "09:11",
              "13:56",
              "14:56",
              "15:32",
              "15:56",
              "16:32",
              "16:56",
              "17:28",
              "17:58"
            ],
            "weekend": [
              "23:06"
            ]
          }
        },
        {
          "name": "Rudohorská dolná",
          "times": {
            "weekday": [
              "06:10",
              "06:43",
              "07:15",
              "07:43",
              "08:10",
              "08:50",
              "09:12",
              "13:57",
              "14:57",
              "15:33",
              "15:57",
              "16:33",
              "16:57",
              "17:29",
              "17:59"
            ],
            "weekend": [
              "23:07"
            ]
          }
        },
        {
          "name": "Starohorská otočka",
          "times": {
            "weekday": [
              "06:12",
              "06:45",
              "07:17",
              "07:45",
              "08:12",
              "08:52",
              "09:14",
              "13:59",
              "14:59",
              "15:35",
              "15:59",
              "16:35",
              "16:59",
              "17:31",
              "18:01"
            ],
            "weekend": [
              "23:09"
            ]
          }
        }
      ]
    },
    {
      "headsign": "nepremáva do",
      "stops": [
        {
          "name": "Starohorská otočka",
          "times": {
            "weekday": [
              "05:23",
              "05:53",
              "06:23",
              "06:55",
              "07:23",
              "08:00",
              "08:25",
              "13:10",
              "14:10",
              "14:40",
              "15:10",
              "15:40",
              "16:10",
              "16:40"
            ],
            "weekend": []
          }
        },
        {
          "name": "Rudohorská dolná",
          "times": {
            "weekday": [
              "05:24",
              "05:54",
              "06:24",
              "06:56",
              "07:24",
              "08:01",
              "08:26",
              "13:11",
              "14:11",
              "14:41",
              "15:11",
              "15:41",
              "16:11",
              "16:41"
            ],
            "weekend": []
          }
        },
        {
          "name": "Rudohorská stred",
          "times": {
            "weekday": [
              "05:26",
              "05:56",
              "06:26",
              "06:58",
              "07:26",
              "08:03",
              "08:28",
              "13:13",
              "14:13",
              "14:43",
              "15:13",
              "15:43",
              "16:13",
              "16:43"
            ],
            "weekend": []
          }
        },
        {
          "name": "Karpatská",
          "times": {
            "weekday": [
              "05:28",
              "05:58",
              "06:28",
              "07:00",
              "07:28",
              "08:05",
              "08:30",
              "13:15",
              "14:15",
              "14:45",
              "15:15",
              "15:45",
              "16:15",
              "16:45"
            ],
            "weekend": []
          }
        },
        {
          "name": "Sásovská cesta",
          "times": {
            "weekday": [
              "05:30",
              "06:00",
              "06:30",
              "07:02",
              "07:30",
              "08:07",
              "08:32",
              "13:17",
              "14:17",
              "14:47",
              "15:17",
              "15:47",
              "16:17",
              "16:47"
            ],
            "weekend": []
          }
        },
        {
          "name": "Sásová,ihrisko",
          "times": {
            "weekday": [
              "05:31",
              "06:01",
              "06:31",
              "07:03",
              "07:31",
              "08:08",
              "08:33",
              "13:18",
              "14:18",
              "14:48",
              "15:18",
              "15:48",
              "16:18",
              "16:48"
            ],
            "weekend": []
          }
        },
        {
          "name": "Na Karlove",
          "times": {
            "weekday": [
              "05:33",
              "06:03",
              "06:33",
              "07:05",
              "07:33",
              "08:10",
              "08:35",
              "13:20",
              "14:20",
              "14:50",
              "15:20",
              "15:50",
              "16:20",
              "16:50"
            ],
            "weekend": []
          }
        },
        {
          "name": "Komenského",
          "times": {
            "weekday": [
              "05:34",
              "06:04",
              "06:34",
              "07:06",
              "07:34",
              "08:11",
              "08:36",
              "13:21",
              "14:21",
              "14:51",
              "15:21",
              "15:51",
              "16:21",
              "16:51"
            ],
            "weekend": []
          }
        },
        {
          "name": "Severná",
          "times": {
            "weekday": [
              "05:36",
              "06:06",
              "06:36",
              "07:08",
              "07:36",
              "08:13",
              "08:38",
              "13:23",
              "14:23",
              "14:53",
              "15:23",
              "15:53",
              "16:23",
              "16:53"
            ],
            "weekend": []
          }
        },
        {
          "name": "Lazovná",
          "times": {
            "weekday": [
              "05:37",
              "06:07",
              "06:37",
              "07:09",
              "07:37",
              "08:14",
              "08:39",
              "13:24",
              "14:24",
              "14:54",
              "15:24",
              "15:54",
              "16:24",
              "16:54"
            ],
            "weekend": []
          }
        },
        {
          "name": "Strieborné námestie",
          "times": {
            "weekday": [
              "05:38",
              "06:08",
              "06:38",
              "07:10",
              "07:38",
              "08:15",
              "08:40",
              "13:25",
              "14:25",
              "14:55",
              "15:25",
              "15:55",
              "16:25",
              "16:55"
            ],
            "weekend": []
          }
        },
        {
          "name": "Tajovského,park",
          "times": {
            "weekday": [
              "02:39"
            ],
            "weekend": []
          }
        },
        {
          "name": "Tajovského školy",
          "times": {
            "weekday": [
              "05:41",
              "06:11",
              "06:41",
              "07:13",
              "07:41",
              "08:18",
              "08:43",
              "13:28",
              "14:28",
              "14:58",
              "15:28",
              "15:58",
              "16:28",
              "16:58"
            ],
            "weekend": []
          }
        },
        {
          "name": "Tajovského,UMB",
          "times": {
            "weekday": [
              "05:42",
              "06:12",
              "06:42",
              "07:14",
              "07:42",
              "08:19",
              "08:44",
              "13:29",
              "14:29",
              "14:59",
              "15:29",
              "15:59",
              "16:29",
              "16:59"
            ],
            "weekend": []
          }
        },
        {
          "name": "Tajovského pod nemocnicou",
          "times": {
            "weekday": [
              "05:43",
              "06:13",
              "06:43",
              "07:15",
              "07:43",
              "08:20",
              "08:45",
              "13:30",
              "14:30",
              "15:00",
              "15:30",
              "16:00",
              "16:30",
              "17:00"
            ],
            "weekend": []
          }
        },
        {
          "name": "Podlavická cesta",
          "times": {
            "weekday": [
              "05:44",
              "06:14",
              "06:44",
              "07:16",
              "07:44",
              "08:21",
              "08:46",
              "13:31",
              "14:31",
              "15:01",
              "15:31",
              "16:01",
              "16:31",
              "17:01"
            ],
            "weekend": []
          }
        },
        {
          "name": "Podlavice,Gaštanová",
          "times": {
            "weekday": [
              "05:46",
              "06:16",
              "06:46",
              "07:18",
              "07:46",
              "08:23",
              "08:48",
              "13:33",
              "14:33",
              "15:03",
              "15:33",
              "16:03",
              "16:33",
              "17:03"
            ],
            "weekend": []
          }
        },
        {
          "name": "nepremáva do",
          "times": {
            "weekday": [
              "02:02",
              "20:26",
              "22:02"
            ],
            "weekend": []
          }
        }
      ]
    }
  ]
}